{
	"name": "Incrementalelectronics",
	"properties": {
		"activities": [
			{
				"name": "lastload",
				"type": "Lookup",
				"dependsOn": [],
				"policy": {
					"timeout": "0.12:00:00",
					"retry": 0,
					"retryIntervalInSeconds": 30,
					"secureOutput": false,
					"secureInput": false
				},
				"userProperties": [],
				"typeProperties": {
					"source": {
						"type": "AzureSqlSource",
						"queryTimeout": "02:00:00",
						"partitionOption": "None"
					},
					"dataset": {
						"referenceName": "electronicssqldbDS",
						"type": "DatasetReference",
						"parameters": {
							"schema": "dbo",
							"table": "watermarktable"
						}
					}
				}
			},
			{
				"name": "currentload",
				"type": "Lookup",
				"dependsOn": [],
				"policy": {
					"timeout": "0.12:00:00",
					"retry": 0,
					"retryIntervalInSeconds": 30,
					"secureOutput": false,
					"secureInput": false
				},
				"userProperties": [],
				"typeProperties": {
					"source": {
						"type": "AzureSqlSource",
						"sqlReaderQuery": "select max(Order_Date) as current_load from [dbo].[sales_raw]",
						"queryTimeout": "02:00:00",
						"partitionOption": "None"
					},
					"dataset": {
						"referenceName": "electronicssqldbDS",
						"type": "DatasetReference",
						"parameters": {
							"schema": "dbo",
							"table": "sales_raw"
						}
					}
				}
			},
			{
				"name": "Incremantalload",
				"type": "Copy",
				"dependsOn": [
					{
						"activity": "lastload",
						"dependencyConditions": [
							"Succeeded"
						]
					},
					{
						"activity": "currentload",
						"dependencyConditions": [
							"Succeeded"
						]
					}
				],
				"policy": {
					"timeout": "0.12:00:00",
					"retry": 0,
					"retryIntervalInSeconds": 30,
					"secureOutput": false,
					"secureInput": false
				},
				"userProperties": [],
				"typeProperties": {
					"source": {
						"type": "AzureSqlSource",
						"sqlReaderQuery": {
							"value": "select * from dbo.sales_raw where Order_Date >'@{activity('lastload').output.firstRow.LAST_LOAD}' and  Order_Date <='@{activity('currentload').output.firstRow.current_load}'",
							"type": "Expression"
						},
						"queryTimeout": "02:00:00",
						"partitionOption": "None"
					},
					"sink": {
						"type": "ParquetSink",
						"storeSettings": {
							"type": "AzureBlobFSWriteSettings"
						},
						"formatSettings": {
							"type": "ParquetWriteSettings"
						}
					},
					"enableStaging": false,
					"translator": {
						"type": "TabularTranslator",
						"typeConversion": true,
						"typeConversionSettings": {
							"allowDataTruncation": true,
							"treatBooleanAsNumber": false
						}
					}
				},
				"inputs": [
					{
						"referenceName": "electronicssqldbDS",
						"type": "DatasetReference",
						"parameters": {
							"schema": "dbo",
							"table": "sales_raw"
						}
					}
				],
				"outputs": [
					{
						"referenceName": "ParquetdatalakeDS",
						"type": "DatasetReference"
					}
				]
			},
			{
				"name": "Updatewatermarktable",
				"type": "SqlServerStoredProcedure",
				"dependsOn": [
					{
						"activity": "Incremantalload",
						"dependencyConditions": [
							"Succeeded"
						]
					}
				],
				"policy": {
					"timeout": "0.12:00:00",
					"retry": 0,
					"retryIntervalInSeconds": 30,
					"secureOutput": false,
					"secureInput": false
				},
				"userProperties": [],
				"typeProperties": {
					"storedProcedureName": "[dbo].[watermarktableupdate]",
					"storedProcedureParameters": {
						"LAST_LOAD": {
							"value": {
								"value": "@activity('currentload').output.firstRow.current_load",
								"type": "Expression"
							},
							"type": "DateTime"
						}
					}
				},
				"linkedServiceName": {
					"referenceName": "electronicssqldbLS",
					"type": "LinkedServiceReference"
				}
			}
		],
		"annotations": [],
		"lastPublishTime": "2026-02-17T14:47:56Z"
	},
	"type": "Microsoft.DataFactory/factories/pipelines"
}